PyramidClass/Alphatriangle.py
PyramidClass/Alphatriangle2.py
PyramidClass/Rtriangle.py
PyramidClass/Rtriangle2.py
PyramidClass/Triangle.py
PyramidClass/__init__.py
DPyramid-0.0.1.dist-info/LICENSE
DPyramid-0.0.1.dist-info/METADATA
DPyramid-0.0.1.dist-info/WHEEL
DPyramid-0.0.1.dist-info/top_level.txt
DPyramid-0.0.1.dist-info/RECORD
