Metadata-Version: 2.1
Name: DPyramid
Version: 0.0.1
Summary: DPyramid
Author: Divya Prakash
Author-email: dprakash050@gmail.com
Keywords: arithmetic,math,pyramid ,python tutorial,tiangle 
Classifier: Development Status :: 1 - Planning
Classifier: Intended Audience :: Developers
Classifier: Programming Language :: Python :: 3
Classifier: Operating System :: Unix
Classifier: Operating System :: MacOS :: MacOS X
Classifier: Operating System :: Microsoft :: Windows
License-File: LICENSE
